[
    {"teacher_id": 1, "teacher_name": "Dr. Brijmohan Daga"},
    {"teacher_id": 2, "teacher_name": "Prof Prajakta Dhamsankar"},
    {"teacher_id": 3, "teacher_name": "Prof Kranti Wagle"},
    {"teacher_id": 4, "teacher_name": "Dr Sunil Surve"},
    {"teacher_id": 5, "teacher_name": "Prof Prachi Patil"},
    {"teacher_id": 6, "teacher_name": "Gajendra Davis"},
    {"teacher_id": 7, "teacher_name": "Dr. Laura Davis"},
    {"teacher_id": 8, "teacher_name": "Dr. Robert Lee"},
    {"teacher_id": 9, "teacher_name": "Dr. Maria Garcia"},
    {"teacher_id": 10, "teacher_name": "Dr. William Taylor"}
]
